{
  "services": [
    {
      "id": "frontal-ponytail",
      "name": "Frontal Ponytail",
      "description": "Please come with your hair as straight as possible. NEW LACES ONLY UNLESS THE ORIGINAL INSTALL WAS DONE HERE! PLEASE DROP YOUR LACE OFF THE DAY BEFORE BY 5PM.",
      "duration": 90,
      "price": 180,
      "category": "hair",
      "popular": true,
      "requirements": ["Hair as straight as possible", "New laces only (unless original install was done here)", "Drop off lace day before by 5PM"],
      "includes": ["Frontal ponytail installation", "Basic styling"],
      "addons": [
        {
          "id": "color-tracks",
          "name": "Add tracks of color provided by client",
          "description": "Additional color tracks from client",
          "price": 10,
          "duration": 10
        },
        {
          "id": "bob-cut",
          "name": "Bob cut",
          "description": "Professional bob cut styling",
          "price": 20,
          "duration": 15
        },
        {
          "id": "braids-on-wig",
          "name": "Braids on a wig",
          "description": "Braiding service on wig",
          "price": 10,
          "duration": 15
        },
        {
          "id": "crimps",
          "name": "Crimps",
          "description": "Crimp styling",
          "price": 20,
          "duration": 20
        },
        {
          "id": "curls",
          "name": "Curls",
          "description": "Curl styling",
          "price": 15,
          "duration": 20
        },
        {
          "id": "fish-tail",
          "name": "Fish tail",
          "description": "Fish tail styling",
          "price": 0,
          "duration": 10
        },
        {
          "id": "layered-curls",
          "name": "Layered curls",
          "description": "Layered curl styling",
          "price": 15,
          "duration": 20
        },
        {
          "id": "left-side-part",
          "name": "Left side part",
          "description": "Free for customization purpose",
          "price": 0,
          "duration": 0
        },
        {
          "id": "middle-part",
          "name": "Middle part",
          "description": "Free for customization purpose",
          "price": 0,
          "duration": 0
        },
        {
          "id": "pinned-curls",
          "name": "Pinned curls (clips included)",
          "description": "Pinned curl styling with clips",
          "price": 25,
          "duration": 20
        },
        {
          "id": "right-side-part",
          "name": "Right side part",
          "description": "Free for customization purpose",
          "price": 0,
          "duration": 0
        },
        {
          "id": "swoop",
          "name": "Swoop",
          "description": "Swoop styling",
          "price": 0,
          "duration": 0
        },
        {
          "id": "up-and-down",
          "name": "Up and down",
          "description": "Up and down styling",
          "price": 10,
          "duration": 10
        },
        {
          "id": "up-do-wig",
          "name": "Up do on a regular wig install",
          "description": "Up do styling on regular wig",
          "price": 15,
          "duration": 20
        },
        {
          "id": "wand-curls",
          "name": "Wand curls",
          "description": "Wand curl styling",
          "price": 15,
          "duration": 20
        },
        {
          "id": "widows-peak",
          "name": "Widows peak",
          "description": "For customization purposes",
          "price": 0,
          "duration": 0
        }
      ]
    },
    {
      "id": "double-frontal-ponytail",
      "name": "Double Frontal Ponytail",
      "description": "Please come with your hair straightened!! NEW LACES ONLY UNLESS THE ORIGINAL INSTALL WAS DONE HERE! PLEASE DROP YOUR LACE OFF THE DAY BEFORE BY 5PM.",
      "duration": 120,
      "price": 200,
      "category": "hair",
      "popular": true,
      "requirements": ["Hair straightened", "New laces only (unless original install was done here)", "Drop off lace day before by 5PM"],
      "includes": ["Double frontal ponytail installation", "Basic styling"],
      "addons": [
        {
          "id": "color-tracks",
          "name": "Add tracks of color provided by client",
          "description": "Additional color tracks from client",
          "price": 10,
          "duration": 10
        },
        {
          "id": "bob-cut",
          "name": "Bob cut",
          "description": "Professional bob cut styling",
          "price": 20,
          "duration": 15
        },
        {
          "id": "braids-on-wig",
          "name": "Braids on a wig",
          "description": "Braiding service on wig",
          "price": 10,
          "duration": 15
        },
        {
          "id": "crimps",
          "name": "Crimps",
          "description": "Crimp styling",
          "price": 20,
          "duration": 20
        },
        {
          "id": "curls",
          "name": "Curls",
          "description": "Curl styling",
          "price": 15,
          "duration": 20
        },
        {
          "id": "fish-tail",
          "name": "Fish tail",
          "description": "Fish tail styling",
          "price": 0,
          "duration": 10
        },
        {
          "id": "layered-curls",
          "name": "Layered curls",
          "description": "Layered curl styling",
          "price": 15,
          "duration": 20
        },
        {
          "id": "left-side-part",
          "name": "Left side part",
          "description": "Free for customization purpose",
          "price": 0,
          "duration": 0
        },
        {
          "id": "middle-part",
          "name": "Middle part",
          "description": "Free for customization purpose",
          "price": 0,
          "duration": 0
        },
        {
          "id": "pinned-curls",
          "name": "Pinned curls (clips included)",
          "description": "Pinned curl styling with clips",
          "price": 25,
          "duration": 20
        },
        {
          "id": "right-side-part",
          "name": "Right side part",
          "description": "Free for customization purpose",
          "price": 0,
          "duration": 0
        },
        {
          "id": "swoop",
          "name": "Swoop",
          "description": "Swoop styling",
          "price": 0,
          "duration": 0
        },
        {
          "id": "up-and-down",
          "name": "Up and down",
          "description": "Up and down styling",
          "price": 10,
          "duration": 10
        },
        {
          "id": "up-do-wig",
          "name": "Up do on a regular wig install",
          "description": "Up do styling on regular wig",
          "price": 15,
          "duration": 20
        },
        {
          "id": "wand-curls",
          "name": "Wand curls",
          "description": "Wand curl styling",
          "price": 15,
          "duration": 20
        },
        {
          "id": "widows-peak",
          "name": "Widows peak",
          "description": "For customization purposes",
          "price": 0,
          "duration": 0
        }
      ]
    },
    {
      "id": "frontal-quick-weave",
      "name": "Frontal Quick Weave",
      "description": "YOUR LACE MUST BE NEW! UNLESS THE ORIGINAL INSTALL WAS DONE HERE. A frontal and 2-3 bundles are needed for this look. Your hair will be braided down, a cap will be applied, your bundles will be glued with track glue and your frontal will be glued with adhesive.",
      "duration": 140,
      "price": 140,
      "category": "hair",
      "requirements": ["New lace (unless original install was done here)", "Frontal and 2-3 bundles needed"],
      "includes": ["Hair braiding", "Cap application", "Bundle installation with track glue", "Frontal installation with adhesive"],
      "addons": [
        {
          "id": "color-tracks",
          "name": "Add tracks of color provided by client",
          "description": "Additional color tracks from client",
          "price": 10,
          "duration": 10
        },
        {
          "id": "bob-cut",
          "name": "Bob cut",
          "description": "Professional bob cut styling",
          "price": 20,
          "duration": 15
        },
        {
          "id": "braids-on-wig",
          "name": "Braids on a wig",
          "description": "Braiding service on wig",
          "price": 10,
          "duration": 15
        },
        {
          "id": "crimps",
          "name": "Crimps",
          "description": "Crimp styling",
          "price": 20,
          "duration": 20
        },
        {
          "id": "curls",
          "name": "Curls",
          "description": "Curl styling",
          "price": 15,
          "duration": 20
        },
        {
          "id": "fish-tail",
          "name": "Fish tail",
          "description": "Fish tail styling",
          "price": 0,
          "duration": 10
        },
        {
          "id": "layered-curls",
          "name": "Layered curls",
          "description": "Layered curl styling",
          "price": 15,
          "duration": 20
        },
        {
          "id": "left-side-part",
          "name": "Left side part",
          "description": "Free for customization purpose",
          "price": 0,
          "duration": 0
        },
        {
          "id": "middle-part",
          "name": "Middle part",
          "description": "Free for customization purpose",
          "price": 0,
          "duration": 0
        },
        {
          "id": "pinned-curls",
          "name": "Pinned curls (clips included)",
          "description": "Pinned curl styling with clips",
          "price": 25,
          "duration": 20
        },
        {
          "id": "right-side-part",
          "name": "Right side part",
          "description": "Free for customization purpose",
          "price": 0,
          "duration": 0
        },
        {
          "id": "swoop",
          "name": "Swoop",
          "description": "Swoop styling",
          "price": 0,
          "duration": 0
        },
        {
          "id": "up-and-down",
          "name": "Up and down",
          "description": "Up and down styling",
          "price": 10,
          "duration": 10
        },
        {
          "id": "up-do-wig",
          "name": "Up do on a regular wig install",
          "description": "Up do styling on regular wig",
          "price": 15,
          "duration": 20
        },
        {
          "id": "wand-curls",
          "name": "Wand curls",
          "description": "Wand curl styling",
          "price": 15,
          "duration": 20
        },
        {
          "id": "widows-peak",
          "name": "Widows peak",
          "description": "For customization purposes",
          "price": 0,
          "duration": 0
        }
      ]
    },
    {
      "id": "closure-quickweave",
      "name": "Closure Quickweave",
      "description": "Professional closure quick weave installation for a natural look.",
      "duration": 90,
      "price": 120,
      "category": "hair",
      "requirements": ["Bring closure and bundles"],
      "includes": ["Closure quick weave installation", "Basic styling"],
      "addons": [
        {
          "id": "color-tracks",
          "name": "Add tracks of color provided by client",
          "description": "Additional color tracks from client",
          "price": 10,
          "duration": 10
        },
        {
          "id": "bob-cut",
          "name": "Bob cut",
          "description": "Professional bob cut styling",
          "price": 20,
          "duration": 15
        },
        {
          "id": "braids-on-wig",
          "name": "Braids on a wig",
          "description": "Braiding service on wig",
          "price": 10,
          "duration": 15
        },
        {
          "id": "crimps",
          "name": "Crimps",
          "description": "Crimp styling",
          "price": 20,
          "duration": 20
        },
        {
          "id": "curls",
          "name": "Curls",
          "description": "Curl styling",
          "price": 15,
          "duration": 20
        },
        {
          "id": "fish-tail",
          "name": "Fish tail",
          "description": "Fish tail styling",
          "price": 0,
          "duration": 10
        },
        {
          "id": "layered-curls",
          "name": "Layered curls",
          "description": "Layered curl styling",
          "price": 15,
          "duration": 20
        },
        {
          "id": "left-side-part",
          "name": "Left side part",
          "description": "Free for customization purpose",
          "price": 0,
          "duration": 0
        },
        {
          "id": "middle-part",
          "name": "Middle part",
          "description": "Free for customization purpose",
          "price": 0,
          "duration": 0
        },
        {
          "id": "pinned-curls",
          "name": "Pinned curls (clips included)",
          "description": "Pinned curl styling with clips",
          "price": 25,
          "duration": 20
        },
        {
          "id": "right-side-part",
          "name": "Right side part",
          "description": "Free for customization purpose",
          "price": 0,
          "duration": 0
        },
        {
          "id": "swoop",
          "name": "Swoop",
          "description": "Swoop styling",
          "price": 0,
          "duration": 0
        },
        {
          "id": "up-and-down",
          "name": "Up and down",
          "description": "Up and down styling",
          "price": 10,
          "duration": 10
        },
        {
          "id": "up-do-wig",
          "name": "Up do on a regular wig install",
          "description": "Up do styling on regular wig",
          "price": 15,
          "duration": 20
        },
        {
          "id": "wand-curls",
          "name": "Wand curls",
          "description": "Wand curl styling",
          "price": 15,
          "duration": 20
        },
        {
          "id": "widows-peak",
          "name": "Widows peak",
          "description": "For customization purposes",
          "price": 0,
          "duration": 0
        }
      ]
    },
    {
      "id": "quick-weave-leave-out",
      "name": "Quick Weave with Leave Out",
      "description": "Quick weave installation with natural hair leave out for a seamless blend.",
      "duration": 90,
      "price": 100,
      "category": "hair",
      "requirements": ["Bring bundles"],
      "includes": ["Quick weave with leave out installation", "Basic styling"],
      "addons": [
        {
          "id": "color-tracks",
          "name": "Add tracks of color provided by client",
          "description": "Additional color tracks from client",
          "price": 10,
          "duration": 10
        },
        {
          "id": "bob-cut",
          "name": "Bob cut",
          "description": "Professional bob cut styling",
          "price": 20,
          "duration": 15
        },
        {
          "id": "braids-on-wig",
          "name": "Braids on a wig",
          "description": "Braiding service on wig",
          "price": 10,
          "duration": 15
        },
        {
          "id": "crimps",
          "name": "Crimps",
          "description": "Crimp styling",
          "price": 20,
          "duration": 20
        },
        {
          "id": "curls",
          "name": "Curls",
          "description": "Curl styling",
          "price": 15,
          "duration": 20
        },
        {
          "id": "fish-tail",
          "name": "Fish tail",
          "description": "Fish tail styling",
          "price": 0,
          "duration": 10
        },
        {
          "id": "layered-curls",
          "name": "Layered curls",
          "description": "Layered curl styling",
          "price": 15,
          "duration": 20
        },
        {
          "id": "left-side-part",
          "name": "Left side part",
          "description": "Free for customization purpose",
          "price": 0,
          "duration": 0
        },
        {
          "id": "middle-part",
          "name": "Middle part",
          "description": "Free for customization purpose",
          "price": 0,
          "duration": 0
        },
        {
          "id": "pinned-curls",
          "name": "Pinned curls (clips included)",
          "description": "Pinned curl styling with clips",
          "price": 25,
          "duration": 20
        },
        {
          "id": "right-side-part",
          "name": "Right side part",
          "description": "Free for customization purpose",
          "price": 0,
          "duration": 0
        },
        {
          "id": "swoop",
          "name": "Swoop",
          "description": "Swoop styling",
          "price": 0,
          "duration": 0
        },
        {
          "id": "up-and-down",
          "name": "Up and down",
          "description": "Up and down styling",
          "price": 10,
          "duration": 10
        },
        {
          "id": "up-do-wig",
          "name": "Up do on a regular wig install",
          "description": "Up do styling on regular wig",
          "price": 15,
          "duration": 20
        },
        {
          "id": "wand-curls",
          "name": "Wand curls",
          "description": "Wand curl styling",
          "price": 15,
          "duration": 20
        },
        {
          "id": "widows-peak",
          "name": "Widows peak",
          "description": "For customization purposes",
          "price": 0,
          "duration": 0
        }
      ]
    },
    {
      "id": "small-bob-knotless",
      "name": "Small Bob Knotless Braids",
      "description": "Small size bob knotless braids for a neat, protective style.",
      "duration": 270,
      "price": 130,
      "category": "braids",
      "requirements": ["Hair must be freshly washed and blow-dried", "No oils or products (grease free)"],
      "includes": ["Braiding service", "Edge styling"]
    },
    {
      "id": "smedium-bob-knotless",
      "name": "Smedium Bob Knotless Braids",
      "description": "Small-to-medium size bob knotless braids.",
      "duration": 210,
      "price": 150,
      "category": "braids",
      "requirements": ["Hair must be freshly washed and blow-dried", "No oils or products (grease free)"],
      "includes": ["Braiding service", "Edge styling"]
    },
    {
      "id": "medium-bob-knotless",
      "name": "Medium Bob Knotless Braids",
      "description": "Medium size bob knotless braids.",
      "duration": 210,
      "price": 100,
      "category": "braids",
      "requirements": ["Hair must be freshly washed and blow-dried", "No oils or products (grease free)"],
      "includes": ["Braiding service", "Edge styling"]
    },
    {
      "id": "smedium-bohemian-knotless",
      "name": "Smedium Bohemian Knotless Braids",
      "description": "Small-to-medium bohemian knotless braids. This is 4-5 pieces of curly hair added to one braid. 2 bundles recommended. Only morning appointments!",
      "duration": 420,
      "price": 200,
      "category": "braids",
      "popular": true,
      "requirements": ["Hair must be freshly washed and blow-dried", "No oils or products (grease free)", "2 bundles recommended", "Morning appointments only"],
      "includes": ["Braiding service", "Curly hair integration", "Edge styling"]
    },
    {
      "id": "medium-bohemian-knotless",
      "name": "Medium Bohemian Knotless Braids",
      "description": "Medium bohemian knotless braids. This is 4-5 pieces of curly hair added to one braid. 2 bundles recommended. Only morning appointments!",
      "duration": 390,
      "price": 180,
      "category": "braids",
      "popular": true,
      "requirements": ["Hair must be freshly washed and blow-dried", "No oils or products (grease free)", "2 bundles recommended", "Morning appointments only"],
      "includes": ["Braiding service", "Curly hair integration", "Edge styling"]
    },
    {
      "id": "small-bohemian",
      "name": "Small Bohemian Braids",
      "description": "Small bohemian braids. This is 4-5 pieces of curly hair added to one braid. 2 bundles recommended. Only morning appointments!",
      "duration": 540,
      "price": 250,
      "category": "braids",
      "requirements": ["Hair must be freshly washed and blow-dried", "No oils or products (grease free)", "2 bundles recommended", "Morning appointments only"],
      "includes": ["Braiding service", "Curly hair integration", "Edge styling"]
    },
    {
      "id": "feed-in-4-6",
      "name": "4-6 Feed In Braids",
      "description": "4-6 feed in braids. Standard length to waist length.",
      "duration": 120,
      "price": 80,
      "category": "braids",
      "requirements": ["Hair must be freshly washed and blow-dried", "No oils or products (grease free)"],
      "includes": ["Braiding service", "Edge styling"]
    },
    {
      "id": "feed-in-8-10",
      "name": "8-10 Feed In Braids",
      "description": "8-10 feed in braids. Standard length to waist length.",
      "duration": 180,
      "price": 100,
      "category": "braids",
      "requirements": ["Hair must be freshly washed and blow-dried", "No oils or products (grease free)"],
      "includes": ["Braiding service", "Edge styling"]
    },
    {
      "id": "alicia-key-braids",
      "name": "Alicia Key Braids",
      "description": "Alicia Key style braids. Standard length to waist length.",
      "duration": 270,
      "price": 150,
      "category": "braids",
      "requirements": ["Hair must be freshly washed and blow-dried", "No oils or products (grease free)"],
      "includes": ["Braiding service", "Edge styling"]
    },
    {
      "id": "fulani-braids",
      "name": "Fulani Braids",
      "description": "Traditional Fulani braids. Only morning appointments!",
      "duration": 360,
      "price": 170,
      "category": "braids",
      "requirements": ["Hair must be freshly washed and blow-dried", "No oils or products (grease free)", "Morning appointments only"],
      "includes": ["Braiding service", "Edge styling"]
    },
    {
      "id": "flip-over-fulani",
      "name": "Flip Over Fulani Braids",
      "description": "Flip over style Fulani braids. Only morning appointments!",
      "duration": 360,
      "price": 170,
      "category": "braids",
      "requirements": ["Hair must be freshly washed and blow-dried", "No oils or products (grease free)", "Morning appointments only"],
      "includes": ["Braiding service", "Edge styling"]
    },
    {
      "id": "fulani-sew-in",
      "name": "Fulani Sew In",
      "description": "Fulani style with sew in. This style requires 2-3 bundles.",
      "duration": 270,
      "price": 150,
      "category": "braids",
      "requirements": ["Hair must be freshly washed and blow-dried", "No oils or products (grease free)", "2-3 bundles required"],
      "includes": ["Braiding service", "Sew in installation", "Edge styling"]
    },
    {
      "id": "lemonade-fulani",
      "name": "Lemonade Fulani Braids",
      "description": "Lemonade style Fulani braids.",
      "duration": 360,
      "price": 200,
      "category": "braids",
      "popular": true,
      "requirements": ["Hair must be freshly washed and blow-dried", "No oils or products (grease free)"],
      "includes": ["Braiding service", "Edge styling"]
    },
    {
      "id": "lemonade-fulani-bob",
      "name": "Lemonade Fulani Bob Braids",
      "description": "Lemonade style Fulani bob braids.",
      "duration": 300,
      "price": 150,
      "category": "braids",
      "requirements": ["Hair must be freshly washed and blow-dried", "No oils or products (grease free)"],
      "includes": ["Braiding service", "Edge styling"]
    },
    {
      "id": "fulani-sew-in-half-wig",
      "name": "Fulani Sew In (Half Wig)",
      "description": "Fulani style sew in as half wig.",
      "duration": 240,
      "price": 100,
      "category": "braids",
      "requirements": ["Hair must be freshly washed and blow-dried", "No oils or products (grease free)"],
      "includes": ["Braiding service", "Half wig installation", "Edge styling"]
    },
    {
      "id": "small-goddess-braids",
      "name": "Small Goddess Braids",
      "description": "Small goddess braids. Standard length to waist length. Only morning appointments!",
      "duration": 450,
      "price": 250,
      "category": "braids",
      "requirements": ["Hair must be freshly washed and blow-dried", "No oils or products (grease free)", "Morning appointments only"],
      "includes": ["Braiding service", "Edge styling"]
    },
    {
      "id": "smedium-goddess-braids",
      "name": "Smedium Goddess Braids",
      "description": "Small-to-medium goddess braids. Standard length to waist length. Only morning appointments!",
      "duration": 360,
      "price": 200,
      "category": "braids",
      "requirements": ["Hair must be freshly washed and blow-dried", "No oils or products (grease free)", "Morning appointments only"],
      "includes": ["Braiding service", "Edge styling"]
    },
    {
      "id": "medium-goddess-braids",
      "name": "Medium Goddess Braids",
      "description": "Medium goddess braids. Standard length to waist length. Only morning appointments!",
      "duration": 330,
      "price": 150,
      "category": "braids",
      "requirements": ["Hair must be freshly washed and blow-dried", "No oils or products (grease free)", "Morning appointments only"],
      "includes": ["Braiding service", "Edge styling"]
    },
    {
      "id": "large-goddess-braids",
      "name": "Large Goddess Braids",
      "description": "Large goddess braids. Standard length to waist length.",
      "duration": 270,
      "price": 100,
      "category": "braids",
      "requirements": ["Hair must be freshly washed and blow-dried", "No oils or products (grease free)"],
      "includes": ["Braiding service", "Edge styling"]
    },
    {
      "id": "classic-sew-in",
      "name": "Classic Sew In",
      "description": "Classic sew in style. This style requires 3 bundles.",
      "duration": 210,
      "price": 100,
      "category": "sew-in",
      "requirements": ["Hair must be freshly washed and blow-dried", "No oils or products (grease free)", "3 bundles required"],
      "includes": ["Cornrow braiding", "Sew in installation", "Basic styling"]
    },
    {
      "id": "versatile-sew-in",
      "name": "Versatile Sew In",
      "description": "Versatile sew in style. This style requires 2-3 bundles.",
      "duration": 210,
      "price": 100,
      "category": "sew-in",
      "requirements": ["Hair must be freshly washed and blow-dried", "No oils or products (grease free)", "2-3 bundles required"],
      "includes": ["Cornrow braiding", "Sew in installation", "Basic styling"]
    },
    {
      "id": "flip-over-sew-in",
      "name": "Flip Over Sew In",
      "description": "Flip over sew in style. This style requires 3 bundles.",
      "duration": 210,
      "price": 100,
      "category": "sew-in",
      "requirements": ["Hair must be freshly washed and blow-dried", "No oils or products (grease free)", "3 bundles required"],
      "includes": ["Cornrow braiding", "Sew in installation", "Basic styling"]
    }
  ],
  "businessHours": {
    "monday": { "open": "09:00", "close": "17:00", "closed": false },
    "tuesday": { "open": "09:00", "close": "19:00", "closed": false },
    "wednesday": { "open": "09:00", "close": "19:00", "closed": false },
    "thursday": { "open": "09:00", "close": "19:00", "closed": false },
    "friday": { "open": "09:00", "close": "20:00", "closed": false },
    "saturday": { "open": "08:00", "close": "20:00", "closed": false },
    "sunday": { "open": "10:00", "close": "17:00", "closed": false }
  },
  "settings": {
    "minimumBookingGap": 0,
    "maxAdvanceBookingDays": 30,
    "defaultServiceDuration": 120,
    "taxRate": 0,
    "cancellationPolicyHours": 48,
    "depositAmount": 30,
    "lunchBreak": null,
    "bufferTime": 0,
    "allowSameDayBooking": true,
    "sundayPremiumFee": 20,
    "emergencyAppointmentFee": 30
  },
  "policies": {
    "welcome": "Thank you for taking an interest in booking with Laidbyoma! By booking with us you agree to the policies listed below.",
    "location": "Located in Dallas, Texas. Open for studio and home services. Address will be sent 48 hours prior to appointment. It is vital that your email is correct. Plus ones are not allowed.",
    "booking": "All appointments are released on the 15th of every month for the following month at 7pm.",
    "deposit": "A non-refundable deposit of $30 is required to secure your booking. The remaining balance will be collected in cash. There is a no refund policy.",
    "cancellation": "Cancellations/rescheduling must be done at least 48 hours prior to appointment or you will be charged. If you cancel your appointment 24 hours before, same day cancellation or no show, you will be charged 50% of the remaining fee.",
    "lateness": "A grace period of 10 minutes will be allowed. After 10 minutes $10 will be charged and for every 5 minutes an additional $5 will be charged. Any later than 25 minutes will result in appointment being cancelled with no refund of deposit.",
    "premium": "Sunday slots are premium with an additional fee of $20. Emergency appointments are an additional fee of $30. Any appointments released that are not on the booking site will be classed as a premium slot ($20). Appointments made 24hrs before desired date are considered emergency appointments.",
    "hairPreparation": "Hair MUST be freshly washed and blow-dried. Failure to do so will lead to being sent home and the appointment cancelled. Please ensure you turn up to appointment with no oils or products (grease free) as it will affect the outcome of your hair when it's done.",
    "payment": "The remaining balance will be collected in cash. Please ensure you have the correct amount."
  }
}
